DSCO/mux2to1.v
module mux2to1(
input a,
input b,
input s,
output reg f
);
always@(*)
	begin
		if(s==1'b0)
			f=a;
		if(s==1'b1)
			f=b;
	end
endmodule

mux4to1.v
`include "mux2to1.v"
module mux4to1(
input [3:0]d,
input [1:0]s,
output f
);
wire f1,f2;
mux2to1 e1(d[3],d[2],s[0],f1);
mux2to1 e2(d[1],d[0],s[0],f2);
mux2to1 e(f1,f2,s[1],f);
endmodule

three_bit_majority.v
`include "mux4to1.v"
module three_bit_majority(
input [2:0]a,
output f
);
mux4to1 m1({1'b1,a[0],a[0],1'b0},{a[2],a[1]},f);
endmodule

three_bit_majority_tb.v
`include "three_bit_majority.v"
`timescale 1ns/1ns
module three_bit_majority_tb();
reg [2:0]a;
wire f;

three_bit_majority e(a,f);

initial begin
	$dumpfile("three_bit_majority.vcd");
	$dumpvars(0,three_bit_majority_tb);
        a = 3'b000; #10;
        a = 3'b001; #10;
        a = 3'b010; #10;
        a = 3'b011; #10;
        a = 3'b100; #10;
        a = 3'b101; #10;
        a = 3'b110; #10;
        a = 3'b111; #10;
end
endmodule

DSCO/three_bit_majority.vcd
$date
	Mon Sep  8 01:39:55 2025
$end
$version
	Icarus Verilog
$end
$timescale
	1ns
$end
$scope module three_bit_majority_tb $end
$var wire 1 ! f $end
$var reg 3 " a [2:0] $end
$scope module e $end
$var wire 3 # a [2:0] $end
$var wire 1 ! f $end
$scope module m1 $end
$var wire 4 $ d [3:0] $end
$var wire 2 % s [1:0] $end
$var wire 1 & f2 $end
$var wire 1 ' f1 $end
$var wire 1 ! f $end
$scope module e $end
$var wire 1 ( s $end
$var wire 1 & b $end
$var wire 1 ' a $end
$var reg 1 ! f $end
$upscope $end
$scope module e1 $end
$var wire 1 ) a $end
$var wire 1 * b $end
$var wire 1 + s $end
$var reg 1 ' f $end
$upscope $end
$scope module e2 $end
$var wire 1 , a $end
$var wire 1 - b $end
$var wire 1 . s $end
$var reg 1 & f $end
$upscope $end
$upscope $end
$upscope $end
$upscope $end
$enddefinitions $end
$comment Show the parameter values. $end
$dumpall
$end
#0
$dumpvars
0.
0-
0,
0+
0*
1)
0(
1'
0&
b0 %
b1000 $
b0 #
b0 "
1!
$end
#10
1&
1*
1,
b1110 $
b1 "
b1 #
#20
0!
0'
0&
0*
0,
1+
1.
b1000 $
b1 %
b10 "
b10 #
#30
1!
1'
1*
1,
b1110 $
b11 "
b11 #
#40
0!
0*
0,
1(
0+
0.
b1000 $
b10 %
b100 "
b100 #
#50
1!
1&
1*
1,
b1110 $
b101 "
b101 #
#60
0!
0'
0&
0*
0,
1+
1.
b1000 $
b11 %
b110 "
b110 #
#70
1'
1*
1,
b1110 $
b111 "
b111 #
