DSCO/mux2to1.v
module mux2to1(
input a,
input b,
input s,
output reg f
);
always@(*)
	begin
		if(s==1'b0)
			f=a;
		if(s==1'b1)
			f=b;
	end
endmodule

DSCO/mux8to1.v
module mux8to1(
input [7:0]d,
input [2:0]s,
output reg f
);
always @ (*)
	begin
	case (s)
	3'b000:f=d[0];
	3'b001:f=d[1];
	3'b010:f=d[2];
	3'b011:f=d[3];
	3'b100:f=d[4];
	3'b101:f=d[5];
	3'b110:f=d[6];
	3'b111:f=d[7];
	
	endcase
end
endmodule

DSCO/mux16to1.v
`include "mux8to1.v"
`include "mux2to1.v"
module mux16to1(
input [15:0]d,
input [3:0]s,
output f
);

wire [1:0]x;
mux8to1 e1(d[7:0],s[2:0],x[0]);
mux8to1 e2(d[15:8],s[2:0],x[1]);
mux2to1 e(x[0],x[1],s[3],f);
endmodule

DSCO/mux16to1_tb.v
`timescale 1ns/1ns
`include "mux16to1.v"
module mux16to1_tb();

reg [15:0]d;
reg [3:0]s;
wire f;

mux16to1 e(d,s,f);

initial begin
	$dumpfile("mux16to1.vcd");
	$dumpvars(0,mux16to1_tb);
	d=16'b1010_1000_0101_0001;
	s=4'b1010;
	#10;
	d=16'b1011_1100_0111_0001;
	s=4'b1000;
	#10;
	for (integer i = 0; i < 16; i = i + 1) begin
        s = i;
        #10;
    	end
    
	$finish;
	end
	endmodule

mux16to1.vcd
$date
	Sun Sep  7 23:09:06 2025
$end
$version
	Icarus Verilog
$end
$timescale
	1ns
$end
$scope module mux16to1_tb $end
$var wire 1 ! f $end
$var reg 16 " d [15:0] $end
$var reg 4 # s [3:0] $end
$scope module e $end
$var wire 16 $ d [15:0] $end
$var wire 4 % s [3:0] $end
$var wire 2 & x [1:0] $end
$var wire 1 ! f $end
$scope module e $end
$var wire 1 ' a $end
$var wire 1 ( b $end
$var wire 1 ) s $end
$var reg 1 ! f $end
$upscope $end
$scope module e1 $end
$var wire 8 * d [7:0] $end
$var wire 3 + s [2:0] $end
$var reg 1 , f $end
$upscope $end
$scope module e2 $end
$var wire 8 - d [7:0] $end
$var wire 3 . s [2:0] $end
$var reg 1 / f $end
$upscope $end
$upscope $end
$scope begin $ivl_for_loop0 $end
$var integer 32 0 i [31:0] $end
$upscope $end
$upscope $end
$enddefinitions $end
$comment Show the parameter values. $end
$dumpall
$end
#0
$dumpvars
bx 0
0/
b10 .
b10101000 -
0,
b10 +
b1010001 *
1)
0(
0'
b0 &
b1010 %
b1010100001010001 $
b1010 #
b1010100001010001 "
0!
$end
#10
1'
b1 &
1,
b0 +
b0 .
b1110001 *
b10111100 -
b1000 #
b1000 %
b1011110001110001 "
b1011110001110001 $
#20
1!
0)
b0 #
b0 %
b0 0
#30
0!
0'
b0 &
0,
b1 +
b1 .
b1 #
b1 %
b1 0
#40
1(
b10 &
1/
b10 +
b10 .
b10 #
b10 %
b10 0
#50
b11 +
b11 .
b11 #
b11 %
b11 0
#60
1!
1'
b11 &
1,
b100 +
b100 .
b100 #
b100 %
b100 0
#70
b101 +
b101 .
b101 #
b101 %
b101 0
#80
0(
b1 &
0/
b110 +
b110 .
b110 #
b110 %
b110 0
#90
0!
0'
1(
0,
b10 &
1/
b111 +
b111 .
b111 #
b111 %
b111 0
#100
1'
0(
1,
b1 &
0/
0!
b0 +
b0 .
1)
b1000 #
b1000 %
b1000 0
#110
0'
b0 &
0,
b1 +
b1 .
b1001 #
b1001 %
b1001 0
#120
1!
1(
b10 &
1/
b10 +
b10 .
b1010 #
b1010 %
b1010 0
#130
b11 +
b11 .
b1011 #
b1011 %
b1011 0
#140
1'
b11 &
1,
b100 +
b100 .
b1100 #
b1100 %
b1100 0
#150
b101 +
b101 .
b1101 #
b1101 %
b1101 0
#160
0!
0(
b1 &
0/
b110 +
b110 .
b1110 #
b1110 %
b1110 0
#170
1!
0'
1(
0,
b10 &
1/
b111 +
b111 .
b1111 #
b1111 %
b1111 0
#180
b10000 0
